alime/__init__.py
alime/__main__.py
alime/generate.py
alime/templates.py
alime-0.1.1.dist-info/LICENSE.txt
alime-0.1.1.dist-info/METADATA
alime-0.1.1.dist-info/WHEEL
alime-0.1.1.dist-info/entry_points.txt
alime-0.1.1.dist-info/top_level.txt
alime-0.1.1.dist-info/RECORD
