Metadata-Version: 2.1
Name: alime
Version: 0.1.1
Summary: Animated anti-bot email obfuscation for your website
Home-page: https://github.com/cduck/alime
Author: Casey Duckering
License: UNKNOWN
Download-URL: https://github.com/cduck/alime/archive/0.1.1.tar.gz
Keywords: html,css,email,scrape
Platform: UNKNOWN
Classifier: License :: OSI Approved :: MIT License
Classifier: Development Status :: 3 - Alpha
Classifier: Programming Language :: Python :: 3
Classifier: Programming Language :: Python :: 3.7
Classifier: Programming Language :: Python :: 3.8
Classifier: Framework :: IPython
Classifier: Framework :: Jupyter
